<RestClientRequest>
  <option name="biscuits">
    <list />
  </option>
  <option name="httpMethod" value="GET" />
  <option name="urlBase" value="http://localhost:8080" />
  <option name="urlPath" value="/vexdashboard/vexboxs/556bf6c830049d12af1c90ea" />
  <option name="headers">
    <list>
      <KeyValuePair>
        <option name="key" value="Authorization" />
        <option name="value" value="Bearer INTEGRATIONTESTBEARERTOKEN" />
      </KeyValuePair>
      <KeyValuePair>
        <option name="key" value="Accept" />
        <option name="value" value="application/json" />
      </KeyValuePair>
    </list>
  </option>
  <option name="parameters">
    <list>
      <KeyValuePair>
        <option name="key" value="o" />
        <option name="value" value="1ea15585-1075-4833-86c6-9321695b5ce4" />
      </KeyValuePair>
    </list>
  </option>
  <option name="parametersEnabled" value="true" />
  <option name="haveTextToSend" value="false" />
  <option name="haveFileToSend" value="false" />
  <option name="isFileUpload" value="false" />
  <option name="textToSend" value="{   &quot;organizationId&quot; : “1ea15585-1075-4833-86c6-9321695b5ce4”,   &quot;publishStatus&quot; : &quot;PUBLISHED&quot;,   &quot;ipaddress&quot; : &quot;192.168.204.3&quot;,   &quot;cpu&quot; : &quot;Intel Core8&quot;,   &quot;memory&quot; : &quot;16G&quot;,   &quot;diskSize&quot; : &quot;256G&quot;,   &quot;javaVersion&quot; : &quot;1.7.0&quot;,   &quot;applicationType&quot; : &quot;COREVEX&quot;,   &quot;applicatonVersion&quot; : &quot;2.3.1&quot;,   &quot;thresholds&quot; : [ {     &quot;type&quot; : &quot;CPU&quot;,     &quot;value&quot; : 40.0   }, {     &quot;type&quot; : &quot;MEMORY&quot;,     &quot;value&quot; : 80.0   } ] } " />
  <option name="filesToSend" value="" />
</RestClientRequest>